kedro_datasentinel/__init__.py
kedro_datasentinel/core.py
kedro_datasentinel/utils.py
kedro_datasentinel/config/__init__.py
kedro_datasentinel/config/data_sentinel_session.py
kedro_datasentinel/config/data_validation.py
kedro_datasentinel/framework/__init__.py
kedro_datasentinel/framework/cli/__init__.py
kedro_datasentinel/framework/cli/cli.py
kedro_datasentinel/framework/hooks/__init__.py
kedro_datasentinel/framework/hooks/datasentinel_hooks.py
kedro_datasentinel/framework/hooks/kedro_audit_row.py
kedro_datasentinel/template/datasentinel.yml
kedro_datasentinel-0.0.1b2.dist-info/licenses/LICENSE
kedro_datasentinel-0.0.1b2.dist-info/METADATA
kedro_datasentinel-0.0.1b2.dist-info/WHEEL
kedro_datasentinel-0.0.1b2.dist-info/entry_points.txt
kedro_datasentinel-0.0.1b2.dist-info/top_level.txt
kedro_datasentinel-0.0.1b2.dist-info/RECORD
