Metadata-Version: 2.4
Name: kedro-datasentinel
Version: 0.0.1b2
Summary: A Kedro plugin to integrate Data Sentinel in Kedro projects.
Author: Sumz SAS
License: Apache Software License (Apache 2.0)
Project-URL: Homepage, https://github.com/SumzCol/kedro-datasentinel
Project-URL: Bug Tracker, https://github.com/SumzCol/kedro-datasentinel/issues
Keywords: data quality,data engineering,kedro,kedro-plugin,data-sentinel
Classifier: Programming Language :: Python :: 3.10
Classifier: Programming Language :: Python :: 3.11
Classifier: Programming Language :: Python :: 3.12
Classifier: Programming Language :: Python :: 3.13
Requires-Python: >=3.10
License-File: LICENSE
Requires-Dist: kedro<1.0,>=0.19.0
Requires-Dist: datasentinel<1.0,>=0.1.0
Provides-Extra: test
Requires-Dist: pytest<9.0,>=7.2; extra == "test"
Requires-Dist: pytest-cov<7,>=3; extra == "test"
Requires-Dist: pendulum>=2.1.2; extra == "test"
Requires-Dist: coverage[toml]; extra == "test"
Requires-Dist: pandas<3.0,>=2.0; extra == "test"
Provides-Extra: scripts
Requires-Dist: click==8.1.0; extra == "scripts"
Provides-Extra: lint
Requires-Dist: ruff==0.11.12; extra == "lint"
Requires-Dist: pre-commit<5.0,>=2.9.2; extra == "lint"
Requires-Dist: pyright==1.1.403; extra == "lint"
Dynamic: license-file
